LICENSE
MANIFEST.in
README
README.rst
requirements.txt
setup.py
articles/__init__.py
articles/admin.py
articles/decorators.py
articles/directives.py
articles/feeds.py
articles/forms.py
articles/listeners.py
articles/models.py
articles/tests.py
articles/urls.py
articles/views.py
articles/fixtures/initial_data.json
articles/fixtures/tags.json
articles/fixtures/users.json
articles/locale/en_US/LC_MESSAGES/django.po
articles/management/__init__.py
articles/management/commands/__init__.py
articles/management/commands/check_for_articles_from_email.py
articles/management/commands/convert_categories_to_tags.py
articles/management/commands/convert_comments_to_disqus.py
articles/migrations/0001_initial.py
articles/migrations/0002_auto__add_field_article_auto_tag.py
articles/migrations/0003_auto__add_field_tag_slug.py
articles/migrations/0004_set_tag_slugs.py
articles/migrations/0005_make_slugs_unique.py
articles/migrations/__init__.py
articles/static/css/jquery.autocomplete.css
articles/static/img/indicator.gif
articles/static/js/jquery-1.4.1.min.js
articles/static/js/jquery.autocomplete.pack.js
articles/static/js/jquery.bgiframe.min.js
articles/static/js/tag_autocomplete.js
articles/templates/404.html
articles/templates/base.html
articles/templates/articles/_article_content.html
articles/templates/articles/_articles.html
articles/templates/articles/_comments.html
articles/templates/articles/_meta.html
articles/templates/articles/_tag_cloud.html
articles/templates/articles/article_detail.html
articles/templates/articles/article_list.html
articles/templates/articles/base.html
articles/templates/articles/by_author.html
articles/templates/articles/display_tag.html
articles/templates/articles/in_month.html
articles/templates/articles/uncategorized_article_list.html
articles/templates/feeds/latest_description.html
articles/templates/feeds/latest_title.html
articles/templates/feeds/tags_description.html
articles/templates/feeds/tags_title.html
articles/templatetags/__init__.py
django_articles.egg-info/PKG-INFO
django_articles.egg-info/SOURCES.txt
django_articles.egg-info/dependency_links.txt
django_articles.egg-info/not-zip-safe
django_articles.egg-info/top_level.txt