Metadata-Version: 1.0
Name: django-articles
Version: 2.4.1
Summary: Sophisticated blogging engine for Django-powered sites
Home-page: http://bitbucket.org/codekoala/django-articles/
Author: Josh VanderLinden
Author-email: codekoala at gmail com
License: BSD
Keywords: django,blog,blogging,engine
Platform: UNKNOWN
Classifier: Development Status :: 5 - Production/Stable
Classifier: Environment :: Web Environment
Classifier: Framework :: Django
Classifier: Intended Audience :: Developers
Classifier: Intended Audience :: End Users/Desktop
Classifier: License :: OSI Approved :: BSD License
Classifier: Natural Language :: English
Classifier: Operating System :: OS Independent
Classifier: Programming Language :: Python
Classifier: Topic :: Communications
Classifier: Topic :: Internet :: WWW/HTTP :: Dynamic Content :: News/Diary
